pyglottolog/__init__.py
pyglottolog/__main__.py
pyglottolog/_compat.py
pyglottolog/api.py
pyglottolog/cli_util.py
pyglottolog/fts.py
pyglottolog/homelands.py
pyglottolog/iso.py
pyglottolog/latex.py
pyglottolog/lff.py
pyglottolog/metadata.py
pyglottolog/monster.py
pyglottolog/objects.py
pyglottolog/util.py
pyglottolog/admin_commands/__init__.py
pyglottolog/admin_commands/bib.py
pyglottolog/admin_commands/check.py
pyglottolog/admin_commands/elpubbib.py
pyglottolog/admin_commands/evobib.py
pyglottolog/admin_commands/fix.py
pyglottolog/admin_commands/fixgeojson.py
pyglottolog/admin_commands/isobib.py
pyglottolog/admin_commands/isoretirements.py
pyglottolog/admin_commands/langindex.py
pyglottolog/admin_commands/lff2tree.py
pyglottolog/admin_commands/release.py
pyglottolog/admin_commands/tree2lff.py
pyglottolog/admin_commands/update.py
pyglottolog/admin_commands/updatebib.py
pyglottolog/admin_commands/updatelinks.py
pyglottolog/admin_commands/updatemacroareas.py
pyglottolog/admin_commands/updatemetadata.py
pyglottolog/admin_commands/updatesources.py
pyglottolog/admin_commands/writelanguoidstats.py
pyglottolog/commands/__init__.py
pyglottolog/commands/create.py
pyglottolog/commands/edit.py
pyglottolog/commands/htmlmap.py
pyglottolog/commands/iso2codes.py
pyglottolog/commands/langdatastats.py
pyglottolog/commands/langsearch.py
pyglottolog/commands/languoids.py
pyglottolog/commands/refsearch.py
pyglottolog/commands/searchindex.py
pyglottolog/commands/show.py
pyglottolog/commands/tree.py
pyglottolog/config/__init__.py
pyglottolog/config/aes_sources.ini
pyglottolog/config/aes_status.ini
pyglottolog/config/document_types.ini
pyglottolog/config/editors.ini
pyglottolog/config/language_types.ini
pyglottolog/config/languoid_levels.ini
pyglottolog/config/macroareas.ini
pyglottolog/config/med_types.ini
pyglottolog/config/publication.ini
pyglottolog/data/africa.geojson.gz
pyglottolog/data/asia.geojson.gz
pyglottolog/data/europe.geojson.gz
pyglottolog/data/northamerica.geojson.gz
pyglottolog-3.16.0.dist-info/LICENSE
pyglottolog-3.16.0.dist-info/METADATA
pyglottolog-3.16.0.dist-info/WHEEL
pyglottolog-3.16.0.dist-info/entry_points.txt
pyglottolog-3.16.0.dist-info/top_level.txt
pyglottolog-3.16.0.dist-info/RECORD
