Metadata-Version: 2.1
Name: pyglottolog
Version: 3.16.0
Summary: python package for glottolog data curation
Home-page: https://github.com/glottolog/pyglottolog
Author: Robert Forkel
Author-email: robert_forkel@eva.mpg.de
License: Apache 2.0
Project-URL: Bug Tracker, https://github.com/glottolog/pyglottolog/issues
Keywords: linguistics
Platform: any
Classifier: Development Status :: 5 - Production/Stable
Classifier: Intended Audience :: Developers
Classifier: Intended Audience :: Science/Research
Classifier: Natural Language :: English
Classifier: Operating System :: OS Independent
Classifier: Programming Language :: Python :: 3
Classifier: Programming Language :: Python :: 3.8
Classifier: Programming Language :: Python :: 3.9
Classifier: Programming Language :: Python :: 3.10
Classifier: Programming Language :: Python :: 3.11
Classifier: Programming Language :: Python :: 3.12
Classifier: Programming Language :: Python :: 3.13
Classifier: Programming Language :: Python :: Implementation :: CPython
Classifier: Programming Language :: Python :: Implementation :: PyPy
Classifier: License :: OSI Approved :: Apache Software License
Requires-Python: >=3.8
License-File: LICENSE
Requires-Dist: simplepybtex
Requires-Dist: attrs>=19.2
Requires-Dist: clldutils>=3.15
Requires-Dist: cldfcatalog
Requires-Dist: csvw>=1.5.6
Requires-Dist: pycldf>=1.6.4
Requires-Dist: sqlalchemy<2
Requires-Dist: tqdm
Requires-Dist: latexcodec
Requires-Dist: unidecode
Requires-Dist: whoosh
Requires-Dist: pycountry>=18.12.8
Requires-Dist: termcolor
Requires-Dist: newick>=0.9.2
Requires-Dist: markdown
Requires-Dist: requests
Requires-Dist: nameparser
Requires-Dist: linglit>=0.3
Requires-Dist: cldfzenodo
Requires-Dist: packaging
Provides-Extra: dev
Requires-Dist: tox; extra == "dev"
Requires-Dist: flake8; extra == "dev"
Requires-Dist: wheel>=0.36; extra == "dev"
Requires-Dist: twine; extra == "dev"
Requires-Dist: build; extra == "dev"
Provides-Extra: docs
Requires-Dist: sphinx<7; extra == "docs"
Requires-Dist: sphinx-autodoc-typehints; extra == "docs"
Requires-Dist: sphinx-rtd-theme; extra == "docs"
Provides-Extra: geo
Requires-Dist: shapely; extra == "geo"
Requires-Dist: pyproj; extra == "geo"
Provides-Extra: test
Requires-Dist: pytest>=5; extra == "test"
Requires-Dist: pytest-mock; extra == "test"
Requires-Dist: requests-mock; extra == "test"
Requires-Dist: pytest-cov; extra == "test"
Requires-Dist: coverage>=4.2; extra == "test"
Requires-Dist: shapely; extra == "test"
Requires-Dist: pyproj; extra == "test"
Requires-Dist: python-levenshtein; extra == "test"
